edc_device/__init__.py
edc_device/apps.py
edc_device/constants.py
edc_device/device.py
edc_device/device_permission.py
edc_device/models.py
edc_device/navbars.py
edc_device/signals.py
edc_device/urls.py
edc_device/view_mixins.py
edc_device/views.py
edc_device/templates/edc_device/home.html
edc_device/tests/__init__.py
edc_device/tests/device_test_helper.py
edc_device/tests/models.py
edc_device/tests/urls.py
edc_device/tests/tests/__init__.py
edc_device/tests/tests/test_device.py
edc_device/tests/tests/test_device_permission.py
edc_device/tests/tests/test_model.py
edc_device/tests/tests/test_views.py
edc_device-1.0.1.dist-info/licenses/AUTHORS.rst
edc_device-1.0.1.dist-info/licenses/LICENSE
tests/__init__.py
tests/test_settings.py
tests/etc/user-aes-local.key
tests/etc/user-aes-restricted.key
tests/etc/user-rsa-local-private.pem
tests/etc/user-rsa-local-public.pem
tests/etc/user-rsa-restricted-private.pem
tests/etc/user-rsa-restricted-public.pem
tests/etc/user-salt-local.key
tests/etc/user-salt-restricted.key
edc_device-1.0.1.dist-info/METADATA
edc_device-1.0.1.dist-info/WHEEL
edc_device-1.0.1.dist-info/top_level.txt
edc_device-1.0.1.dist-info/RECORD
